{
  "whatsappPhone": "529994195286",
  "whatsappDefaultMessage": "Hola! Me gustaría información sobre las clases de Pulso Latino",
  "hero": {
    "tagline": "El lugar donde tus sueños encuentran el ritmo",
    "headlinePrefix": "Aprende a",
    "headlineHighlight": "Bailar",
    "subheadline": "Salsa · Bachata · Cumbia<br>2 sucursales en Mérida, Yucatán",
    "primaryCtaLabel": "Informes por WhatsApp",
    "primaryCtaMessage": "Hola! Me gustaría información sobre las clases de Pulso Latino",
    "secondaryCtaLabel": "Empieza a bailar hoy ↓"
  },
  "footer": {
    "locationText": "Av. Madero · Pacabtún · Mérida, Yucatán",
    "whatsappText": "WhatsApp: 999 419 5286",
    "copyrightText": "© 2026 Pulso Latino · Estudio de Danza y Baile Latino",
    "socials": [
      {
        "label": "PulsoLatinoMid",
        "href": "https://www.facebook.com/PulsoLatinoMid"
      },
      {
        "label": "@pulso_latino",
        "href": "https://www.instagram.com/pulso_latino/"
      }
    ]
  },
  "floatingWhatsapp": {
    "label": "Escríbenos",
    "message": "Hola! Me gustaría información sobre las clases de Pulso Latino"
  }
}
